lmcat/__init__.py
lmcat/__main__.py
lmcat/file_stats.py
lmcat/index.html
lmcat/lmcat.py
lmcat/processing_pipeline.py
lmcat/processors.py
lmcat-0.2.0.dist-info/METADATA
lmcat-0.2.0.dist-info/WHEEL
lmcat-0.2.0.dist-info/licenses/LICENSE
lmcat-0.2.0.dist-info/RECORD
