Metadata-Version: 2.4
Name: lmcat
Version: 0.2.0
Summary: concatenating files for tossing them into a language model
Project-URL: Homepage, https://miv.name/lmcat
Project-URL: Documentation, https://miv.name/lmcat
Project-URL: Repository, https://github.com/mivanit/lmcat
Project-URL: Issues, https://github.com/mivanit/lmcat/issues
Author-email: Michael Ivanitskiy <mivanits@umich.edu>
License-File: LICENSE
Requires-Python: >=3.11
Requires-Dist: igittigitt>=2.1.5
Requires-Dist: muutils>=0.6.21
Provides-Extra: tokenizers
Requires-Dist: tokenizers>=0.21.0; extra == 'tokenizers'
